djangodoo/forms.py
djangodoo/fields.py
djangodoo/admin.py
djangodoo/auth.py
djangodoo/tests.py
djangodoo/__init__.py
djangodoo/models.py
djangodoo-0.1.1.dist-info/WHEEL
djangodoo-0.1.1.dist-info/top_level.txt
djangodoo-0.1.1.dist-info/metadata.json
djangodoo-0.1.1.dist-info/RECORD
djangodoo-0.1.1.dist-info/DESCRIPTION.rst
djangodoo-0.1.1.dist-info/METADATA
