Metadata-Version: 2.0
Name: djangodoo
Version: 0.1.1
Summary: A Django app to copy models, load and save records from a running Odoo instance
Home-page: UNKNOWN
Author: François Degrave
Author-email: francois.degrave@unamur.be
License: MIT License
Platform: UNKNOWN
Classifier: Environment :: Web Environment
Classifier: Framework :: Django
Classifier: Intended Audience :: Developers
Classifier: License :: OSI Approved :: MIT License
Classifier: Operating System :: OS Independent
Classifier: Programming Language :: Python
Classifier: Programming Language :: Python :: 2.7
Classifier: Programming Language :: Python :: 3
Classifier: Programming Language :: Python :: 3.2
Classifier: Programming Language :: Python :: 3.3
Classifier: Programming Language :: Python :: 3.4
Classifier: Topic :: Internet :: WWW/HTTP
Requires-Dist: Django (>=1.7.2)
Requires-Dist: ERPpeek (>=1.6)
Requires-Dist: python-memcached
